{
  "protocol_version" : "0.0.6",
  "configuration" : {
    "version" : "(6.13.0) (explicit/331e48ca)",
    "tlc" : "__thread",
    "sigsgev" : "normal",
    "notifications" : "kqueue",
    "architecture" : "arm64",
    "disabled_features" : "com,shared_perfcounters",
    "smallconfig" : "disabled",
    "bigarrays" : "disabled",
    "softdebug" : "enabled",
    "interpreter" : "enabled",
    "llvm_support" : "disabled",
    "suspend" : "preemptive"
  },
  "memory" : {
    "Resident Size" : "673382400",
    "Virtual Size" : "422464618496",
    "minor_gc_time" : "0",
    "major_gc_time" : "1370928",
    "minor_gc_count" : "0",
    "major_gc_count" : "17",
    "major_gc_time_concurrent" : "0"
 },
  "threads" : [
 {
    "is_managed" : false,
    "offset_free_hash" : "0x0",
    "offset_rich_hash" : "0x0",
    "crashed" : false,
    "native_thread_id" : "0x2960cf000",
    "thread_info_addr" : "0x131cf4800",
    "thread_name" : "Thread Pool I/O Selector",
    "ctx" : {
      "IP" : "0x192a8f010",
      "SP" : "0x2960ceaf0",
      "BP" : "0x2960cecf0"
  },
    "unmanaged_frames" : [
  {
      "is_managed" : "false",
      "native_address" : "0x28c840444",
      "native_offset" : "0x00000"
   }
,
  {
      "is_managed" : "false",
      "native_address" : "0x28c975f18",
      "native_offset" : "0x00000"
   }
,
  {
      "is_managed" : "false",
      "native_address" : "0x28c976290",
      "native_offset" : "0x00000"
   }
,
  {
      "is_managed" : "false",
      "native_address" : "0x28c97603c",
      "native_offset" : "0x00000"
   }
,
  {
      "is_managed" : "false",
      "native_address" : "0x28c8813b8",
      "native_offset" : "0x00000"
   }
,
  {
      "is_managed" : "false",
      "native_address" : "0x192af2a24",
      "native_offset" : "0x00000"
   }
,
  {
      "is_managed" : "false",
      "native_address" : "0x28c9c8044",
      "native_offset" : "0x00000"
   }
,
  {
      "is_managed" : "false",
      "native_address" : "0x28c97b524",
      "native_offset" : "0x00000"
   }
,
  {
      "is_managed" : "false",
      "native_address" : "0x28c97aea0",
      "native_offset" : "0x00000"
   }
,
  {
      "is_managed" : "false",
      "native_address" : "0x28c976d00",
      "native_offset" : "0x00000"
   }
,
  {
      "is_managed" : "false",
      "native_address" : "0x28c976bac",
      "native_offset" : "0x00000"
   }
,
  {
      "is_managed" : "false",
      "native_address" : "0x28c9f61d8",
      "native_offset" : "0x00000"
   }
,
  {
      "is_managed" : "false",
      "native_address" : "0x28c9f6160",
      "native_offset" : "0x00000"
   }
,
  {
      "is_managed" : "false",
      "native_address" : "0x192ac3fa8",
      "native_offset" : "0x00000"
   }
,
  {
      "is_managed" : "false",
      "native_address" : "0x192abeda0",
      "native_offset" : "0x00000"
   }

  ]
 },
 {
    "is_managed" : false,
    "offset_free_hash" : "0x0",
    "offset_rich_hash" : "0x0",
    "crashed" : false,
    "native_thread_id" : "0x2a12df000",
    "thread_info_addr" : "0x130363600",
    "thread_name" : "tid_6c23",
    "ctx" : {
      "IP" : "0x192a83eb0",
      "SP" : "0x2a12ded30",
      "BP" : "0x2a12ded40"
  },
    "unmanaged_frames" : [
  {
      "is_managed" : "false",
      "native_address" : "0x28c840444",
      "native_offset" : "0x00000"
   }
,
  {
      "is_managed" : "false",
      "native_address" : "0x28c975f18",
      "native_offset" : "0x00000"
   }
,
  {
      "is_managed" : "false",
      "native_address" : "0x28c976290",
      "native_offset" : "0x00000"
   }
,
  {
      "is_managed" : "false",
      "native_address" : "0x28c97603c",
      "native_offset" : "0x00000"
   }
,
  {
      "is_managed" : "false",
      "native_address" : "0x28c8813b8",
      "native_offset" : "0x00000"
   }
,
  {
      "is_managed" : "false",
      "native_address" : "0x192af2a24",
      "native_offset" : "0x00000"
   }
,
  {
      "is_managed" : "false",
      "native_address" : "0x19291499c",
      "native_offset" : "0x00000"
   }
,
  {
      "is_managed" : "false",
      "native_address" : "0x192915050",
      "native_offset" : "0x00000"
   }
,
  {
      "is_managed" : "false",
      "native_address" : "0x105070c48",
      "native_offset" : "0x00000"
   }
,
  {
      "is_managed" : "false",
      "native_address" : "0x102cf29b0",
      "native_offset" : "0x00000"
   }
,
  {
      "is_managed" : "false",
      "native_address" : "0x102cf3da4",
      "native_offset" : "0x00000"
   }
,
  {
      "is_managed" : "false",
      "native_address" : "0x102f4d3c0",
      "native_offset" : "0x00000"
   }
,
  {
      "is_managed" : "false",
      "native_address" : "0x192ac3fa8",
      "native_offset" : "0x00000"
   }
,
  {
      "is_managed" : "false",
      "native_address" : "0x192abeda0",
      "native_offset" : "0x00000"
   }

  ]
 },
 {
    "is_managed" : false,
    "offset_free_hash" : "0x0",
    "offset_rich_hash" : "0x0",
    "crashed" : false,
    "native_thread_id" : "0x297d8b000",
    "thread_info_addr" : "0x131a25a00",
    "thread_name" : "tid_32e03",
    "ctx" : {
      "IP" : "0x192a83eb0",
      "SP" : "0x297d8adf0",
      "BP" : "0x297d8ae00"
  },
    "unmanaged_frames" : [
  {
      "is_managed" : "false",
      "native_address" : "0x28c840444",
      "native_offset" : "0x00000"
   }
,
  {
      "is_managed" : "false",
      "native_address" : "0x28c975f18",
      "native_offset" : "0x00000"
   }
,
  {
      "is_managed" : "false",
      "native_address" : "0x28c976290",
      "native_offset" : "0x00000"
   }
,
  {
      "is_managed" : "false",
      "native_address" : "0x28c97603c",
      "native_offset" : "0x00000"
   }
,
  {
      "is_managed" : "false",
      "native_address" : "0x28c8813b8",
      "native_offset" : "0x00000"
   }
,
  {
      "is_managed" : "false",
      "native_address" : "0x192af2a24",
      "native_offset" : "0x00000"
   }
,
  {
      "is_managed" : "false",
      "native_address" : "0x19291499c",
      "native_offset" : "0x00000"
   }
,
  {
      "is_managed" : "false",
      "native_address" : "0x192915050",
      "native_offset" : "0x00000"
   }
,
  {
      "is_managed" : "false",
      "native_address" : "0x105070c48",
      "native_offset" : "0x00000"
   }
,
  {
      "is_managed" : "false",
      "native_address" : "0x1029a610c",
      "native_offset" : "0x00000"
   }
,
  {
      "is_managed" : "false",
      "native_address" : "0x102d9b918",
      "native_offset" : "0x00000"
   }
,
  {
      "is_managed" : "false",
      "native_address" : "0x102d9b8b4",
      "native_offset" : "0x00000"
   }
,
  {
      "is_managed" : "false",
      "native_address" : "0x102f4d3c0",
      "native_offset" : "0x00000"
   }
,
  {
      "is_managed" : "false",
      "native_address" : "0x192ac3fa8",
      "native_offset" : "0x00000"
   }
,
  {
      "is_managed" : "false",
      "native_address" : "0x192abeda0",
      "native_offset" : "0x00000"
   }

  ]
 },
 {
    "is_managed" : false,
    "offset_free_hash" : "0x0",
    "offset_rich_hash" : "0x0",
    "crashed" : false,
    "native_thread_id" : "0x301b6f000",
    "thread_info_addr" : "0x130921c00",
    "thread_name" : "Thread Pool Worker",
    "ctx" : {
      "IP" : "0x192a83ec8",
      "SP" : "0x301b6edc0",
      "BP" : "0x301b6ee50"
  },
    "unmanaged_frames" : [
  {
      "is_managed" : "false",
      "native_address" : "0x28c840444",
      "native_offset" : "0x00000"
   }
,
  {
      "is_managed" : "false",
      "native_address" : "0x28c975f18",
      "native_offset" : "0x00000"
   }
,
  {
      "is_managed" : "false",
      "native_address" : "0x28c976290",
      "native_offset" : "0x00000"
   }
,
  {
      "is_managed" : "false",
      "native_address" : "0x28c97603c",
      "native_offset" : "0x00000"
   }
,
  {
      "is_managed" : "false",
      "native_address" : "0x28c8813b8",
      "native_offset" : "0x00000"
   }
,
  {
      "is_managed" : "false",
      "native_address" : "0x192af2a24",
      "native_offset" : "0x00000"
   }
,
  {
      "is_managed" : "false",
      "native_address" : "0x28c8cf11c",
      "native_offset" : "0x00000"
   }
,
  {
      "is_managed" : "false",
      "native_address" : "0x28c976d00",
      "native_offset" : "0x00000"
   }
,
  {
      "is_managed" : "false",
      "native_address" : "0x28c976bac",
      "native_offset" : "0x00000"
   }
,
  {
      "is_managed" : "false",
      "native_address" : "0x28c9f61d8",
      "native_offset" : "0x00000"
   }
,
  {
      "is_managed" : "false",
      "native_address" : "0x28c9f6160",
      "native_offset" : "0x00000"
   }
,
  {
      "is_managed" : "false",
      "native_address" : "0x192ac3fa8",
      "native_offset" : "0x00000"
   }
,
  {
      "is_managed" : "false",
      "native_address" : "0x192abeda0",
      "native_offset" : "0x00000"
   }

  ]
 },
 {
    "is_managed" : true,
    "offset_free_hash" : "0xf2d2c2660",
    "offset_rich_hash" : "0xf2d2c27c7",
    "crashed" : true,
    "native_thread_id" : "0x1edb4e080",
    "thread_info_addr" : "0x130a17000",
    "thread_name" : "tid_103",
    "ctx" : {
      "IP" : "0x19296a764",
      "SP" : "0x16d832490",
      "BP" : "0x16d8324a0"
  },
    "managed_frames" : [
  {
      "is_managed" : "false",
      "native_address" : "unregistered"
   }
,
  {
      "is_managed" : "true",
      "guid" : "E364485C-9F80-4F10-9CF0-077748648452",
      "token" : "0x00000",
      "native_offset" : "0x0",
      "filename" : "UnityEngine.TextCoreFontEngineModule.dll",
      "sizeofimage" : "0x18000",
      "timestamp" : "0xd0cb89d1",
      "il_offset" : "0xffffffff"
   }
,
  {
      "is_managed" : "true",
      "guid" : "E364485C-9F80-4F10-9CF0-077748648452",
      "token" : "0x600008d",
      "native_offset" : "0x0",
      "filename" : "UnityEngine.TextCoreFontEngineModule.dll",
      "sizeofimage" : "0x18000",
      "timestamp" : "0xd0cb89d1",
      "il_offset" : "0x00001"
   }
,
  {
      "is_managed" : "true",
      "guid" : "870658A5-616C-487B-8398-7DF3A32C6198",
      "token" : "0x6000017",
      "native_offset" : "0x0",
      "filename" : "UnityEditor.TextCoreTextEngineModule.dll",
      "sizeofimage" : "0x36000",
      "timestamp" : "0x86c5a58d",
      "il_offset" : "0x0000f"
   }
,
  {
      "is_managed" : "true",
      "guid" : "870658A5-616C-487B-8398-7DF3A32C6198",
      "token" : "0x600000d",
      "native_offset" : "0x0",
      "filename" : "UnityEditor.TextCoreTextEngineModule.dll",
      "sizeofimage" : "0x36000",
      "timestamp" : "0x86c5a58d",
      "il_offset" : "0x000d9"
   }
,
  {
      "is_managed" : "true",
      "guid" : "1079A7BB-DF12-4B90-988B-982EADE8E58C",
      "token" : "0x00000",
      "native_offset" : "0x0",
      "filename" : "mscorlib.dll",
      "sizeofimage" : "0x470000",
      "timestamp" : "0x826b1d59",
      "il_offset" : "0x0002a"
   }
,
  {
      "is_managed" : "false",
      "native_address" : "unregistered"
   }
,
  {
      "is_managed" : "true",
      "guid" : "BB5BA448-D212-48E1-B434-CD0B918DF53C",
      "token" : "0x00000",
      "native_offset" : "0x0",
      "filename" : "UnityEngine.CoreModule.dll",
      "sizeofimage" : "0x1aa000",
      "timestamp" : "0xd3603386",
      "il_offset" : "0xffffffff"
   }
,
  {
      "is_managed" : "true",
      "guid" : "BB5BA448-D212-48E1-B434-CD0B918DF53C",
      "token" : "0x60021a4",
      "native_offset" : "0x0",
      "filename" : "UnityEngine.CoreModule.dll",
      "sizeofimage" : "0x1aa000",
      "timestamp" : "0xd3603386",
      "il_offset" : "0x00001"
   }
,
  {
      "is_managed" : "true",
      "guid" : "42129F9E-2DB7-46A9-BFD1-CB37B0AD1020",
      "token" : "0x60032a6",
      "native_offset" : "0x0",
      "filename" : "UnityEditor.CoreModule.dll",
      "sizeofimage" : "0x968000",
      "timestamp" : "0xe7317058",
      "il_offset" : "0x00027"
   }
,
  {
      "is_managed" : "true",
      "guid" : "42129F9E-2DB7-46A9-BFD1-CB37B0AD1020",
      "token" : "0x60032a7",
      "native_offset" : "0x0",
      "filename" : "UnityEditor.CoreModule.dll",
      "sizeofimage" : "0x968000",
      "timestamp" : "0xe7317058",
      "il_offset" : "0x00001"
   }
,
  {
      "is_managed" : "true",
      "guid" : "42129F9E-2DB7-46A9-BFD1-CB37B0AD1020",
      "token" : "0x60032b3",
      "native_offset" : "0x0",
      "filename" : "UnityEditor.CoreModule.dll",
      "sizeofimage" : "0x968000",
      "timestamp" : "0xe7317058",
      "il_offset" : "0x00001"
   }
,
  {
      "is_managed" : "true",
      "guid" : "42129F9E-2DB7-46A9-BFD1-CB37B0AD1020",
      "token" : "0x60032ae",
      "native_offset" : "0x0",
      "filename" : "UnityEditor.CoreModule.dll",
      "sizeofimage" : "0x968000",
      "timestamp" : "0xe7317058",
      "il_offset" : "0x00001"
   }
,
  {
      "is_managed" : "true",
      "guid" : "870658A5-616C-487B-8398-7DF3A32C6198",
      "token" : "0x600000a",
      "native_offset" : "0x0",
      "filename" : "UnityEditor.TextCoreTextEngineModule.dll",
      "sizeofimage" : "0x36000",
      "timestamp" : "0x86c5a58d",
      "il_offset" : "0x00001"
   }
,
  {
      "is_managed" : "true",
      "guid" : "1079A7BB-DF12-4B90-988B-982EADE8E58C",
      "token" : "0x00000",
      "native_offset" : "0x0",
      "filename" : "mscorlib.dll",
      "sizeofimage" : "0x470000",
      "timestamp" : "0x826b1d59",
      "il_offset" : "0x0002a"
   }

  ],
  "unmanaged_frames" : [
 {
    "is_managed" : "false",
    "native_address" : "0x28c840444",
    "native_offset" : "0x00000"
  }
,
 {
    "is_managed" : "false",
    "native_address" : "0x28c975f18",
    "native_offset" : "0x00000"
  }
,
 {
    "is_managed" : "false",
    "native_address" : "0x28c976290",
    "native_offset" : "0x00000"
  }
,
 {
    "is_managed" : "false",
    "native_address" : "0x28c9768e0",
    "native_offset" : "0x00000"
  }
,
 {
    "is_managed" : "false",
    "native_address" : "0x28c882204",
    "native_offset" : "0x00000"
  }
,
 {
    "is_managed" : "false",
    "native_address" : "0x28c844564",
    "native_offset" : "0x00000"
  }
,
 {
    "is_managed" : "false",
    "native_address" : "0x28c7cce40",
    "native_offset" : "0x00000"
  }
,
 {
    "is_managed" : "false",
    "native_address" : "0x192af2a24",
    "native_offset" : "0x00000"
  }
,
 {
    "is_managed" : "false",
    "native_address" : "0x19296a760",
    "native_offset" : "0x00000"
  }
,
 {
    "is_managed" : "false",
    "native_address" : "0x19296eae0",
    "native_offset" : "0x00000"
  }
,
 {
    "is_managed" : "false",
    "native_address" : "0x104c72708",
    "native_offset" : "0x00000"
  }
,
 {
    "is_managed" : "false",
    "native_address" : "0x104c78fa8",
    "native_offset" : "0x00000"
  }
,
 {
    "is_managed" : "false",
    "native_address" : "0x104ca46dc",
    "native_offset" : "0x00000"
  }
,
 {
    "is_managed" : "false",
    "native_address" : "0x104c7a000",
    "native_offset" : "0x00000"
  }
,
 {
    "is_managed" : "false",
    "native_address" : "0x104c75b00",
    "native_offset" : "0x00000"
  }
,
 {
    "is_managed" : "false",
    "native_address" : "0x10364e470",
    "native_offset" : "0x00000"
  }
,
 {
    "is_managed" : "false",
    "native_address" : "0x1026ca4a0",
    "native_offset" : "0x00000"
  }
,
 {
    "is_managed" : "true",
    "guid" : "E364485C-9F80-4F10-9CF0-077748648452",
    "token" : "0x00000",
    "native_offset" : "0x0",
    "filename" : "UnityEngine.TextCoreFontEngineModule.dll",
    "sizeofimage" : "0x18000",
    "timestamp" : "0xd0cb89d1",
    "il_offset" : "0x00000"
  }
,
 {
    "is_managed" : "true",
    "guid" : "E364485C-9F80-4F10-9CF0-077748648452",
    "token" : "0x600008d",
    "native_offset" : "0x0",
    "filename" : "UnityEngine.TextCoreFontEngineModule.dll",
    "sizeofimage" : "0x18000",
    "timestamp" : "0xd0cb89d1",
    "il_offset" : "0x00000"
  }
,
 {
    "is_managed" : "true",
    "guid" : "870658A5-616C-487B-8398-7DF3A32C6198",
    "token" : "0x6000017",
    "native_offset" : "0x0",
    "filename" : "UnityEditor.TextCoreTextEngineModule.dll",
    "sizeofimage" : "0x36000",
    "timestamp" : "0x86c5a58d",
    "il_offset" : "0x00000"
  }
,
 {
    "is_managed" : "true",
    "guid" : "870658A5-616C-487B-8398-7DF3A32C6198",
    "token" : "0x600000d",
    "native_offset" : "0x0",
    "filename" : "UnityEditor.TextCoreTextEngineModule.dll",
    "sizeofimage" : "0x36000",
    "timestamp" : "0x86c5a58d",
    "il_offset" : "0x00000"
  }
,
 {
    "is_managed" : "true",
    "guid" : "1079A7BB-DF12-4B90-988B-982EADE8E58C",
    "token" : "0x00000",
    "native_offset" : "0x0",
    "filename" : "mscorlib.dll",
    "sizeofimage" : "0x470000",
    "timestamp" : "0x826b1d59",
    "il_offset" : "0x00000"
  }
,
 {
    "is_managed" : "false",
    "native_address" : "0x28c7d0114",
    "native_offset" : "0x00000"
  }
,
 {
    "is_managed" : "false",
    "native_address" : "0x28c954da0",
    "native_offset" : "0x00000"
  }
,
 {
    "is_managed" : "false",
    "native_address" : "0x28c954ce0",
    "native_offset" : "0x00000"
  }
,
 {
    "is_managed" : "false",
    "native_address" : "0x103125814",
    "native_offset" : "0x00000"
  }
,
 {
    "is_managed" : "false",
    "native_address" : "0x103100e00",
    "native_offset" : "0x00000"
  }
,
 {
    "is_managed" : "false",
    "native_address" : "0x103100c88",
    "native_offset" : "0x00000"
  }
,
 {
    "is_managed" : "false",
    "native_address" : "0x1031b681c",
    "native_offset" : "0x00000"
  }
,
 {
    "is_managed" : "false",
    "native_address" : "0x1030c6fa4",
    "native_offset" : "0x00000"
  }
,
 {
    "is_managed" : "false",
    "native_address" : "0x1030c89d8",
    "native_offset" : "0x00000"
  }
,
 {
    "is_managed" : "false",
    "native_address" : "0x1030fdca8",
    "native_offset" : "0x00000"
  }
,
 {
    "is_managed" : "false",
    "native_address" : "0x102626660",
    "native_offset" : "0x00000"
  }
,
 {
    "is_managed" : "true",
    "guid" : "BB5BA448-D212-48E1-B434-CD0B918DF53C",
    "token" : "0x00000",
    "native_offset" : "0x0",
    "filename" : "UnityEngine.CoreModule.dll",
    "sizeofimage" : "0x1aa000",
    "timestamp" : "0xd3603386",
    "il_offset" : "0x00000"
  }
,
 {
    "is_managed" : "true",
    "guid" : "BB5BA448-D212-48E1-B434-CD0B918DF53C",
    "token" : "0x60021a4",
    "native_offset" : "0x0",
    "filename" : "UnityEngine.CoreModule.dll",
    "sizeofimage" : "0x1aa000",
    "timestamp" : "0xd3603386",
    "il_offset" : "0x00000"
  }
,
 {
    "is_managed" : "true",
    "guid" : "42129F9E-2DB7-46A9-BFD1-CB37B0AD1020",
    "token" : "0x60032a6",
    "native_offset" : "0x0",
    "filename" : "UnityEditor.CoreModule.dll",
    "sizeofimage" : "0x968000",
    "timestamp" : "0xe7317058",
    "il_offset" : "0x00000"
  }
,
 {
    "is_managed" : "true",
    "guid" : "42129F9E-2DB7-46A9-BFD1-CB37B0AD1020",
    "token" : "0x60032a7",
    "native_offset" : "0x0",
    "filename" : "UnityEditor.CoreModule.dll",
    "sizeofimage" : "0x968000",
    "timestamp" : "0xe7317058",
    "il_offset" : "0x00000"
  }
,
 {
    "is_managed" : "true",
    "guid" : "42129F9E-2DB7-46A9-BFD1-CB37B0AD1020",
    "token" : "0x60032b3",
    "native_offset" : "0x0",
    "filename" : "UnityEditor.CoreModule.dll",
    "sizeofimage" : "0x968000",
    "timestamp" : "0xe7317058",
    "il_offset" : "0x00000"
  }
,
 {
    "is_managed" : "true",
    "guid" : "42129F9E-2DB7-46A9-BFD1-CB37B0AD1020",
    "token" : "0x60032ae",
    "native_offset" : "0x0",
    "filename" : "UnityEditor.CoreModule.dll",
    "sizeofimage" : "0x968000",
    "timestamp" : "0xe7317058",
    "il_offset" : "0x00000"
  }
,
 {
    "is_managed" : "true",
    "guid" : "870658A5-616C-487B-8398-7DF3A32C6198",
    "token" : "0x600000a",
    "native_offset" : "0x0",
    "filename" : "UnityEditor.TextCoreTextEngineModule.dll",
    "sizeofimage" : "0x36000",
    "timestamp" : "0x86c5a58d",
    "il_offset" : "0x00000"
  }
,
 {
    "is_managed" : "true",
    "guid" : "1079A7BB-DF12-4B90-988B-982EADE8E58C",
    "token" : "0x00000",
    "native_offset" : "0x0",
    "filename" : "mscorlib.dll",
    "sizeofimage" : "0x470000",
    "timestamp" : "0x826b1d59",
    "il_offset" : "0x00000"
  }
,
 {
    "is_managed" : "false",
    "native_address" : "0x28c7d0114",
    "native_offset" : "0x00000"
  }
,
 {
    "is_managed" : "false",
    "native_address" : "0x28c954da0",
    "native_offset" : "0x00000"
  }
,
 {
    "is_managed" : "false",
    "native_address" : "0x28c954ce0",
    "native_offset" : "0x00000"
  }
,
 {
    "is_managed" : "false",
    "native_address" : "0x103125814",
    "native_offset" : "0x00000"
  }
,
 {
    "is_managed" : "false",
    "native_address" : "0x103100e00",
    "native_offset" : "0x00000"
  }
,
 {
    "is_managed" : "false",
    "native_address" : "0x103100c88",
    "native_offset" : "0x00000"
  }
,
 {
    "is_managed" : "false",
    "native_address" : "0x103f0f274",
    "native_offset" : "0x00000"
  }
,
 {
    "is_managed" : "false",
    "native_address" : "0x103f0ec64",
    "native_offset" : "0x00000"
  }
,
 {
    "is_managed" : "false",
    "native_address" : "0x103aa913c",
    "native_offset" : "0x00000"
  }
,
 {
    "is_managed" : "false",
    "native_address" : "0x104f9718c",
    "native_offset" : "0x00000"
  }
,
 {
    "is_managed" : "false",
    "native_address" : "0x195f6f4cc",
    "native_offset" : "0x00000"
  }
,
 {
    "is_managed" : "false",
    "native_address" : "0x19603b498",
    "native_offset" : "0x00000"
  }
,
 {
    "is_managed" : "false",
    "native_address" : "0x19603b214",
    "native_offset" : "0x00000"
  }
,
 {
    "is_managed" : "false",
    "native_address" : "0x196076ba0",
    "native_offset" : "0x00000"
  }
,
 {
    "is_managed" : "false",
    "native_address" : "0x196076ac0",
    "native_offset" : "0x00000"
  }
,
 {
    "is_managed" : "false",
    "native_address" : "0x196076914",
    "native_offset" : "0x00000"
  }
,
 {
    "is_managed" : "false",
    "native_address" : "0x196023828",
    "native_offset" : "0x00000"
  }
,
 {
    "is_managed" : "false",
    "native_address" : "0x19c3cb3a4",
    "native_offset" : "0x00000"
  }
,
 {
    "is_managed" : "false",
    "native_address" : "0x19c3ca828",
    "native_offset" : "0x00000"
  }
,
 {
    "is_managed" : "false",
    "native_address" : "0x19c3e0a40",
    "native_offset" : "0x00000"
  }
,
 {
    "is_managed" : "false",
    "native_address" : "0x19c43e8e4",
    "native_offset" : "0x00000"
  }
,
 {
    "is_managed" : "false",
    "native_address" : "0x19c462564",
    "native_offset" : "0x00000"
  }
,
 {
    "is_managed" : "false",
    "native_address" : "0x19c4624f4",
    "native_offset" : "0x00000"
  }
,
 {
    "is_managed" : "false",
    "native_address" : "0x19c462320",
    "native_offset" : "0x00000"
  }
,
 {
    "is_managed" : "false",
    "native_address" : "0x19c462ce0",
    "native_offset" : "0x00000"
  }
,
 {
    "is_managed" : "false",
    "native_address" : "0x19c462a00",
    "native_offset" : "0x00000"
  }
,
 {
    "is_managed" : "false",
    "native_address" : "0x195f19918",
    "native_offset" : "0x00000"
  }
,
 {
    "is_managed" : "false",
    "native_address" : "0x195f1973c",
    "native_offset" : "0x00000"
  }
,
 {
    "is_managed" : "false",
    "native_address" : "0x195dc7104",
    "native_offset" : "0x00000"
  }
,
 {
    "is_managed" : "false",
    "native_address" : "0x104fa3d20",
    "native_offset" : "0x00000"
  }
,
 {
    "is_managed" : "false",
    "native_address" : "0x193b523f8",
    "native_offset" : "0x00000"
  }
,
 {
    "is_managed" : "false",
    "native_address" : "0x192bbc358",
    "native_offset" : "0x00000"
  }
,
 {
    "is_managed" : "false",
    "native_address" : "0x192bbc000",
    "native_offset" : "0x00000"
  }
,
 {
    "is_managed" : "false",
    "native_address" : "0x192bbbb58",
    "native_offset" : "0x00000"
  }
,
 {
    "is_managed" : "false",
    "native_address" : "0x192ba12d8",
    "native_offset" : "0x00000"
  }
,
 {
    "is_managed" : "false",
    "native_address" : "0x192ba0448",
    "native_offset" : "0x00000"
  }
,
 {
    "is_managed" : "false",
    "native_address" : "0x19c3f2df0",
    "native_offset" : "0x00000"
  }
,
 {
    "is_managed" : "false",
    "native_address" : "0x19c3f2c2c",
    "native_offset" : "0x00000"
  }
,
 {
    "is_managed" : "false",
    "native_address" : "0x19c3f2984",
    "native_offset" : "0x00000"
  }

 ]
},
{
  "is_managed" : false,
  "offset_free_hash" : "0x0",
  "offset_rich_hash" : "0x0",
  "crashed" : false,
  "native_thread_id" : "0x320307000",
  "thread_info_addr" : "0x2982e0400",
  "thread_name" : "Thread Pool Worker",
  "ctx" : {
    "IP" : "0x192a83ec8",
    "SP" : "0x320306dc0",
    "BP" : "0x320306e50"
 },
  "unmanaged_frames" : [
 {
    "is_managed" : "false",
    "native_address" : "0x28c840444",
    "native_offset" : "0x00000"
  }
,
 {
    "is_managed" : "false",
    "native_address" : "0x28c975f18",
    "native_offset" : "0x00000"
  }
,
 {
    "is_managed" : "false",
    "native_address" : "0x28c976290",
    "native_offset" : "0x00000"
  }
,
 {
    "is_managed" : "false",
    "native_address" : "0x28c97603c",
    "native_offset" : "0x00000"
  }
,
 {
    "is_managed" : "false",
    "native_address" : "0x28c8813b8",
    "native_offset" : "0x00000"
  }
,
 {
    "is_managed" : "false",
    "native_address" : "0x192af2a24",
    "native_offset" : "0x00000"
  }
,
 {
    "is_managed" : "false",
    "native_address" : "0x28c8cf11c",
    "native_offset" : "0x00000"
  }
,
 {
    "is_managed" : "false",
    "native_address" : "0x28c976d00",
    "native_offset" : "0x00000"
  }
,
 {
    "is_managed" : "false",
    "native_address" : "0x28c976bac",
    "native_offset" : "0x00000"
  }
,
 {
    "is_managed" : "false",
    "native_address" : "0x28c9f61d8",
    "native_offset" : "0x00000"
  }
,
 {
    "is_managed" : "false",
    "native_address" : "0x28c9f6160",
    "native_offset" : "0x00000"
  }
,
 {
    "is_managed" : "false",
    "native_address" : "0x192ac3fa8",
    "native_offset" : "0x00000"
  }
,
 {
    "is_managed" : "false",
    "native_address" : "0x192abeda0",
    "native_offset" : "0x00000"
  }

 ]
},
{
  "is_managed" : false,
  "offset_free_hash" : "0x0",
  "offset_rich_hash" : "0x0",
  "crashed" : false,
  "native_thread_id" : "0x17e3df000",
  "thread_info_addr" : "0x131fa7400",
  "thread_name" : "tid_1520f",
  "ctx" : {
    "IP" : "0x192a83eb0",
    "SP" : "0x17e3ded30",
    "BP" : "0x17e3ded40"
 },
  "unmanaged_frames" : [
 {
    "is_managed" : "false",
    "native_address" : "0x28c840444",
    "native_offset" : "0x00000"
  }
,
 {
    "is_managed" : "false",
    "native_address" : "0x28c975f18",
    "native_offset" : "0x00000"
  }
,
 {
    "is_managed" : "false",
    "native_address" : "0x28c976290",
    "native_offset" : "0x00000"
  }
,
 {
    "is_managed" : "false",
    "native_address" : "0x28c97603c",
    "native_offset" : "0x00000"
  }
,
 {
    "is_managed" : "false",
    "native_address" : "0x28c8813b8",
    "native_offset" : "0x00000"
  }
,
 {
    "is_managed" : "false",
    "native_address" : "0x192af2a24",
    "native_offset" : "0x00000"
  }
,
 {
    "is_managed" : "false",
    "native_address" : "0x19291499c",
    "native_offset" : "0x00000"
  }
,
 {
    "is_managed" : "false",
    "native_address" : "0x192915050",
    "native_offset" : "0x00000"
  }
,
 {
    "is_managed" : "false",
    "native_address" : "0x105070c48",
    "native_offset" : "0x00000"
  }
,
 {
    "is_managed" : "false",
    "native_address" : "0x102cf29b0",
    "native_offset" : "0x00000"
  }
,
 {
    "is_managed" : "false",
    "native_address" : "0x102cf3da4",
    "native_offset" : "0x00000"
  }
,
 {
    "is_managed" : "false",
    "native_address" : "0x102f4d3c0",
    "native_offset" : "0x00000"
  }
,
 {
    "is_managed" : "false",
    "native_address" : "0x192ac3fa8",
    "native_offset" : "0x00000"
  }
,
 {
    "is_managed" : "false",
    "native_address" : "0x192abeda0",
    "native_offset" : "0x00000"
  }

 ]
},
{
  "is_managed" : false,
  "offset_free_hash" : "0x0",
  "offset_rich_hash" : "0x0",
  "crashed" : false,
  "native_thread_id" : "0x28d067000",
  "thread_info_addr" : "0x13192ba00",
  "thread_name" : "Finalizer",
  "ctx" : {
    "IP" : "0x192a83eb0",
    "SP" : "0x28d066de0",
    "BP" : "0x28d066e50"
 },
  "unmanaged_frames" : [
 {
    "is_managed" : "false",
    "native_address" : "0x28c840444",
    "native_offset" : "0x00000"
  }
,
 {
    "is_managed" : "false",
    "native_address" : "0x28c975f18",
    "native_offset" : "0x00000"
  }
,
 {
    "is_managed" : "false",
    "native_address" : "0x28c976290",
    "native_offset" : "0x00000"
  }
,
 {
    "is_managed" : "false",
    "native_address" : "0x28c97603c",
    "native_offset" : "0x00000"
  }
,
 {
    "is_managed" : "false",
    "native_address" : "0x28c8813b8",
    "native_offset" : "0x00000"
  }
,
 {
    "is_managed" : "false",
    "native_address" : "0x192af2a24",
    "native_offset" : "0x00000"
  }
,
 {
    "is_managed" : "false",
    "native_address" : "0x28c9afab4",
    "native_offset" : "0x00000"
  }
,
 {
    "is_managed" : "false",
    "native_address" : "0x28c976d00",
    "native_offset" : "0x00000"
  }
,
 {
    "is_managed" : "false",
    "native_address" : "0x28c976bac",
    "native_offset" : "0x00000"
  }
,
 {
    "is_managed" : "false",
    "native_address" : "0x28c9f61d8",
    "native_offset" : "0x00000"
  }
,
 {
    "is_managed" : "false",
    "native_address" : "0x28c9f6160",
    "native_offset" : "0x00000"
  }
,
 {
    "is_managed" : "false",
    "native_address" : "0x192ac3fa8",
    "native_offset" : "0x00000"
  }
,
 {
    "is_managed" : "false",
    "native_address" : "0x192abeda0",
    "native_offset" : "0x00000"
  }

 ]
},
{
  "is_managed" : false,
  "offset_free_hash" : "0x0",
  "offset_rich_hash" : "0x0",
  "crashed" : false,
  "native_thread_id" : "0x28d273000",
  "thread_info_addr" : "0x13192e600",
  "thread_name" : "Debugger agent",
  "ctx" : {
    "IP" : "0x192a8c828",
    "SP" : "0x28d272ad0",
    "BP" : "0x28d272af0"
 },
  "unmanaged_frames" : [
 {
    "is_managed" : "false",
    "native_address" : "0x28c840444",
    "native_offset" : "0x00000"
  }
,
 {
    "is_managed" : "false",
    "native_address" : "0x28c975f18",
    "native_offset" : "0x00000"
  }
,
 {
    "is_managed" : "false",
    "native_address" : "0x28c976290",
    "native_offset" : "0x00000"
  }
,
 {
    "is_managed" : "false",
    "native_address" : "0x28c97603c",
    "native_offset" : "0x00000"
  }
,
 {
    "is_managed" : "false",
    "native_address" : "0x28c8813b8",
    "native_offset" : "0x00000"
  }
,
 {
    "is_managed" : "false",
    "native_address" : "0x192af2a24",
    "native_offset" : "0x00000"
  }
,
 {
    "is_managed" : "false",
    "native_address" : "0x28c8adfe8",
    "native_offset" : "0x00000"
  }
,
 {
    "is_managed" : "false",
    "native_address" : "0x28c8a70f0",
    "native_offset" : "0x00000"
  }
,
 {
    "is_managed" : "false",
    "native_address" : "0x28c976d00",
    "native_offset" : "0x00000"
  }
,
 {
    "is_managed" : "false",
    "native_address" : "0x28c976bac",
    "native_offset" : "0x00000"
  }
,
 {
    "is_managed" : "false",
    "native_address" : "0x28c9f61d8",
    "native_offset" : "0x00000"
  }
,
 {
    "is_managed" : "false",
    "native_address" : "0x28c9f6160",
    "native_offset" : "0x00000"
  }
,
 {
    "is_managed" : "false",
    "native_address" : "0x192ac3fa8",
    "native_offset" : "0x00000"
  }
,
 {
    "is_managed" : "false",
    "native_address" : "0x192abeda0",
    "native_offset" : "0x00000"
  }

 ]
},
{
  "is_managed" : false,
  "offset_free_hash" : "0x0",
  "offset_rich_hash" : "0x0",
  "crashed" : false,
  "native_thread_id" : "0x31f62f000",
  "thread_info_addr" : "0x30996a000",
  "thread_name" : "tid_5412f",
  "ctx" : {
    "IP" : "0x192a87730",
    "SP" : "0x31f62ec40",
    "BP" : "0x31f62ecd0"
 },
  "unmanaged_frames" : [
 {
    "is_managed" : "false",
    "native_address" : "0x28c840444",
    "native_offset" : "0x00000"
  }
,
 {
    "is_managed" : "false",
    "native_address" : "0x28c975f18",
    "native_offset" : "0x00000"
  }
,
 {
    "is_managed" : "false",
    "native_address" : "0x28c976290",
    "native_offset" : "0x00000"
  }
,
 {
    "is_managed" : "false",
    "native_address" : "0x28c97603c",
    "native_offset" : "0x00000"
  }
,
 {
    "is_managed" : "false",
    "native_address" : "0x28c8813b8",
    "native_offset" : "0x00000"
  }
,
 {
    "is_managed" : "false",
    "native_address" : "0x192af2a24",
    "native_offset" : "0x00000"
  }
,
 {
    "is_managed" : "false",
    "native_address" : "0x192ac45a0",
    "native_offset" : "0x00000"
  }
,
 {
    "is_managed" : "false",
    "native_address" : "0x28c9c55d0",
    "native_offset" : "0x00000"
  }
,
 {
    "is_managed" : "false",
    "native_address" : "0x28c9cf1b0",
    "native_offset" : "0x00000"
  }
,
 {
    "is_managed" : "false",
    "native_address" : "0x28c8ce950",
    "native_offset" : "0x00000"
  }
,
 {
    "is_managed" : "false",
    "native_address" : "0x28c976d00",
    "native_offset" : "0x00000"
  }
,
 {
    "is_managed" : "false",
    "native_address" : "0x28c976bac",
    "native_offset" : "0x00000"
  }
,
 {
    "is_managed" : "false",
    "native_address" : "0x28c9f61d8",
    "native_offset" : "0x00000"
  }
,
 {
    "is_managed" : "false",
    "native_address" : "0x28c9f6160",
    "native_offset" : "0x00000"
  }
,
 {
    "is_managed" : "false",
    "native_address" : "0x192ac3fa8",
    "native_offset" : "0x00000"
  }
,
 {
    "is_managed" : "false",
    "native_address" : "0x192abeda0",
    "native_offset" : "0x00000"
  }

 ]
},
{
  "is_managed" : false,
  "offset_free_hash" : "0x0",
  "offset_rich_hash" : "0x0",
  "crashed" : false,
  "native_thread_id" : "0x17e46b000",
  "thread_info_addr" : "0x28faf8400",
  "thread_name" : "tid_bb0f",
  "ctx" : {
    "IP" : "0x192a83eb0",
    "SP" : "0x17e46ad30",
    "BP" : "0x17e46ad40"
 },
  "unmanaged_frames" : [
 {
    "is_managed" : "false",
    "native_address" : "0x28c840444",
    "native_offset" : "0x00000"
  }
,
 {
    "is_managed" : "false",
    "native_address" : "0x28c975f18",
    "native_offset" : "0x00000"
  }
,
 {
    "is_managed" : "false",
    "native_address" : "0x28c976290",
    "native_offset" : "0x00000"
  }
,
 {
    "is_managed" : "false",
    "native_address" : "0x28c97603c",
    "native_offset" : "0x00000"
  }
,
 {
    "is_managed" : "false",
    "native_address" : "0x28c8813b8",
    "native_offset" : "0x00000"
  }
,
 {
    "is_managed" : "false",
    "native_address" : "0x192af2a24",
    "native_offset" : "0x00000"
  }
,
 {
    "is_managed" : "false",
    "native_address" : "0x19291499c",
    "native_offset" : "0x00000"
  }
,
 {
    "is_managed" : "false",
    "native_address" : "0x192915050",
    "native_offset" : "0x00000"
  }
,
 {
    "is_managed" : "false",
    "native_address" : "0x105070c48",
    "native_offset" : "0x00000"
  }
,
 {
    "is_managed" : "false",
    "native_address" : "0x102cf29b0",
    "native_offset" : "0x00000"
  }
,
 {
    "is_managed" : "false",
    "native_address" : "0x102cf3da4",
    "native_offset" : "0x00000"
  }
,
 {
    "is_managed" : "false",
    "native_address" : "0x102f4d3c0",
    "native_offset" : "0x00000"
  }
,
 {
    "is_managed" : "false",
    "native_address" : "0x192ac3fa8",
    "native_offset" : "0x00000"
  }
,
 {
    "is_managed" : "false",
    "native_address" : "0x192abeda0",
    "native_offset" : "0x00000"
  }

 ]
},
{
  "is_managed" : false,
  "offset_free_hash" : "0x0",
  "offset_rich_hash" : "0x0",
  "crashed" : false,
  "native_thread_id" : "0x31fd07000",
  "thread_info_addr" : "0x130a66400",
  "thread_name" : "Thread Pool Worker",
  "ctx" : {
    "IP" : "0x192a83ec8",
    "SP" : "0x31fd06dc0",
    "BP" : "0x31fd06e50"
 },
  "unmanaged_frames" : [
 {
    "is_managed" : "false",
    "native_address" : "0x28c840444",
    "native_offset" : "0x00000"
  }
,
 {
    "is_managed" : "false",
    "native_address" : "0x28c975f18",
    "native_offset" : "0x00000"
  }
,
 {
    "is_managed" : "false",
    "native_address" : "0x28c976290",
    "native_offset" : "0x00000"
  }
,
 {
    "is_managed" : "false",
    "native_address" : "0x28c97603c",
    "native_offset" : "0x00000"
  }
,
 {
    "is_managed" : "false",
    "native_address" : "0x28c8813b8",
    "native_offset" : "0x00000"
  }
,
 {
    "is_managed" : "false",
    "native_address" : "0x192af2a24",
    "native_offset" : "0x00000"
  }
,
 {
    "is_managed" : "false",
    "native_address" : "0x28c8cf11c",
    "native_offset" : "0x00000"
  }
,
 {
    "is_managed" : "false",
    "native_address" : "0x28c976d00",
    "native_offset" : "0x00000"
  }
,
 {
    "is_managed" : "false",
    "native_address" : "0x28c976bac",
    "native_offset" : "0x00000"
  }
,
 {
    "is_managed" : "false",
    "native_address" : "0x28c9f61d8",
    "native_offset" : "0x00000"
  }
,
 {
    "is_managed" : "false",
    "native_address" : "0x28c9f6160",
    "native_offset" : "0x00000"
  }
,
 {
    "is_managed" : "false",
    "native_address" : "0x192ac3fa8",
    "native_offset" : "0x00000"
  }
,
 {
    "is_managed" : "false",
    "native_address" : "0x192abeda0",
    "native_offset" : "0x00000"
  }

 ]
},
{
  "is_managed" : false,
  "offset_free_hash" : "0x0",
  "offset_rich_hash" : "0x0",
  "crashed" : false,
  "native_thread_id" : "0x31f83b000",
  "thread_info_addr" : "0x2982d8c00",
  "thread_name" : "Thread Pool Worker",
  "ctx" : {
    "IP" : "0x192a83ec8",
    "SP" : "0x31f83adc0",
    "BP" : "0x31f83ae50"
 },
  "unmanaged_frames" : [
 {
    "is_managed" : "false",
    "native_address" : "0x28c840444",
    "native_offset" : "0x00000"
  }
,
 {
    "is_managed" : "false",
    "native_address" : "0x28c975f18",
    "native_offset" : "0x00000"
  }
,
 {
    "is_managed" : "false",
    "native_address" : "0x28c976290",
    "native_offset" : "0x00000"
  }
,
 {
    "is_managed" : "false",
    "native_address" : "0x28c97603c",
    "native_offset" : "0x00000"
  }
,
 {
    "is_managed" : "false",
    "native_address" : "0x28c8813b8",
    "native_offset" : "0x00000"
  }
,
 {
    "is_managed" : "false",
    "native_address" : "0x192af2a24",
    "native_offset" : "0x00000"
  }
,
 {
    "is_managed" : "false",
    "native_address" : "0x28c8cf11c",
    "native_offset" : "0x00000"
  }
,
 {
    "is_managed" : "false",
    "native_address" : "0x28c976d00",
    "native_offset" : "0x00000"
  }
,
 {
    "is_managed" : "false",
    "native_address" : "0x28c976bac",
    "native_offset" : "0x00000"
  }
,
 {
    "is_managed" : "false",
    "native_address" : "0x28c9f61d8",
    "native_offset" : "0x00000"
  }
,
 {
    "is_managed" : "false",
    "native_address" : "0x28c9f6160",
    "native_offset" : "0x00000"
  }
,
 {
    "is_managed" : "false",
    "native_address" : "0x192ac3fa8",
    "native_offset" : "0x00000"
  }
,
 {
    "is_managed" : "false",
    "native_address" : "0x192abeda0",
    "native_offset" : "0x00000"
  }

 ]
}
]
}